MigurdiaPy/__init__.py
MigurdiaPy/migurdia.py
MigurdiaPy-0.0.1.dist-info/LICENSE
MigurdiaPy-0.0.1.dist-info/METADATA
MigurdiaPy-0.0.1.dist-info/WHEEL
MigurdiaPy-0.0.1.dist-info/top_level.txt
MigurdiaPy-0.0.1.dist-info/RECORD
